attachments_model/__init__.py
attachments_model/attachments.py
attachments_model/domino.py
sysnet_attachments_model-1.0.16.dist-info/licenses/LICENSE
sysnet_attachments_model-1.0.16.dist-info/METADATA
sysnet_attachments_model-1.0.16.dist-info/WHEEL
sysnet_attachments_model-1.0.16.dist-info/top_level.txt
sysnet_attachments_model-1.0.16.dist-info/RECORD
